dist_along_route-0.1.0.dist-info/METADATA
dist_along_route-0.1.0.dist-info/WHEEL
dist_along_route-0.1.0.dist-info/entry_points.txt
dist_along_route/__init__.py
dist_along_route/path.py
dist_along_route/route.py
dist_along_route-0.1.0.dist-info/RECORD
