Metadata-Version: 2.1
Name: dist-along-route
Version: 0.1.0
Summary: dist-along-route determines the distance of a point along a defined route, with both specified in GPS coords
Author-Email: ThisTemba <tembamateke@gmail.com>
License: MIT
Requires-Python: >=3.12
Requires-Dist: numpy>=2.3.2
Requires-Dist: scipy>=1.16.1
Requires-Dist: coordstometers>=0.0.4
Provides-Extra: dev
Requires-Dist: pytest>=8.4.1; extra == "dev"
